baobzi-0.9.6.data/data/lib/libbaobzi.so
baobzi-0.9.6.data/data/share/baobzi/julia/baobzi.jl
baobzi-0.9.6.data/data/include/baobzi.hpp
baobzi-0.9.6.data/data/include/baobzi.h
baobzi-0.9.6.data/data/include/baobzi_template.hpp
baobzi-0.9.6.data/data/include/baobzi/baobzi_decls.h
baobzi-0.9.6.data/data/include/baobzi/baobzi_cases.h
baobzi-0.9.6.data/data/include/baobzi/header.h
baobzi-0.9.6.data/data/include/baobzi/macros.h
baobzi-0.9.6.data/data/include/baobzi/baobzi_cases_restore.h
baobzi-0.9.6.data/data/include/baobzi/eigen_matrix_plugin.h
baobzi.libs/libstdc++-a9383cce.so.6.0.28
baobzi.libs/libgcc_s-a04fdf82.so.1
baobzi/__init__.py
baobzi-0.9.6.dist-info/METADATA
baobzi-0.9.6.dist-info/WHEEL
baobzi-0.9.6.dist-info/top_level.txt
baobzi-0.9.6.dist-info/RECORD
baobzi-0.9.6.dist-info/LICENSE
