Metadata-Version: 2.1
Name: baobzi
Version: 0.9.6
Summary: An adaptive fast function approximator based on tree search
Home-page: https://github.com/flatironinstitute/baobzi
Author: Robert Blackwell
Author-email: rblackwell@flatironinstitute.org
License-File: LICENSE
Requires-Dist: numpy
